[
  {
    "name": "Cream Western Suit Set",
    "price": 2000,
    "gender": "men",
    "category": "clothing",
    "subcategory": "suits",
    "imageUrl": "su1.jpeg",
    "description": "Classic cream western two-piece suit, suitable for reception parties or semi-formal functions.",
    "stylistNotes": "Pair with a white shirt and brown leather loafers for an understated yet classy finish.",
    "materialCare": "Use steam iron. Store with suit cover.",
    "size": "L",
    "ownerName": "Aditya Sharma",
    "availableDays": 3,
    "id": "8658047e-50a2-4b02-8024-2b804e0264e6",
    "status": "available"
  },
  {
    "name": "Classic Black Tuxedo",
    "price": 4500,
    "gender": "men",
    "category": "clothing",
    "subcategory": "suits",
    "imageUrl": "su2.jpeg",
    "description": "A timeless double-breasted black tuxedo with satin lapels, ideal for evening receptions and black-tie events.",
    "stylistNotes": "Pair with patent leather shoes and a sleek watch for a refined look.",
    "materialCare": "Dry clean only. Steam lightly before wearing.",
    "size": "M",
    "ownerName": "Aryan Kapoor",
    "availableDays": 5,
    "id": "75d45745-3ee1-427b-aa06-5066f9bc43ef",
    "status": "available"
  },
  {
    "name": "Modern Blue Casual Suit",
    "price": 2800,
    "gender": "men",
    "category": "clothing",
    "subcategory": "suits",
    "imageUrl": "su3.jpeg",
    "description": "Stylish and comfortable slim-fit blue suit paired with a white T-shirt for casual yet smart events.",
    "stylistNotes": "Perfect for engagement parties or day events. Complete with sneakers for a fresh urban vibe.",
    "materialCare": "Machine wash cold, dry clean for best results.",
    "size": "L",
    "ownerName": "Ritik Mehra",
    "availableDays": 4,
    "id": "6703f17b-7c52-4c70-8ff0-46fcf4782247",
    "status": "available"
  },
  {
    "name": "Olive Green Regal Suit",
    "price": 5000,
    "gender": "men",
    "category": "clothing",
    "subcategory": "suits",
    "imageUrl": "su4.jpeg",
    "description": "A statement double-breasted olive suit with sharp tailoring for modern groomsmen or cocktail evenings.",
    "stylistNotes": "Pair with a patterned pocket square and polished brogues for an elegant finish.",
    "materialCare": "Dry clean only.",
    "size": "M",
    "ownerName": "Devansh Tiwari",
    "availableDays": 6,
    "id": "99ea5c14-4a83-4630-af40-7f3363f371a7",
    "status": "unavailable"
  }
]